insightflow/__init__.py
insightflow/_version.py
insightflow/settings.py
insightflow/core/__init__.py
insightflow/core/compose.py
insightflow/core/generate_queries.py
insightflow/core/prompts.py
insightflow/core/research.py
insightflow/core/search.py
insightflow/core/utils.py
insightflow/interfaces/__init__.py
insightflow/interfaces/__main__.py
insightflow/interfaces/api.py
insightflow/interfaces/cli.py
insightflow/interfaces/mcp.py
insightflow/models/__init__.py
insightflow/models/llm_config.py
insightflow/models/llm_result.py
insightflow/models/queries.py
insightflow/models/report.py
insightflow-0.2.0.dist-info/METADATA
insightflow-0.2.0.dist-info/WHEEL
insightflow-0.2.0.dist-info/entry_points.txt
insightflow-0.2.0.dist-info/licenses/LICENSE
insightflow-0.2.0.dist-info/RECORD
