Metadata-Version: 2.4
Name: insightflow
Version: 0.2.0
Summary: A research automation tool that searches and analyzes web content, papers, blogs, and social media to generate comprehensive reports for given queries
Project-URL: Homepage, https://github.com/sync-dev-org/insightflow
Project-URL: Repository, https://github.com/sync-dev-org/insightflow
Project-URL: Issues, https://github.com/sync-dev-org/insightflow/issues
Project-URL: Documentation, https://github.com/sync-dev-org/insightflow#readme
Author-email: minamikik <mia@sync.dev>
Maintainer-email: minamikik <mia@sync.dev>
License: MIT
License-File: LICENSE
Keywords: ai,analysis,automation,llm,report-generation,research
Classifier: Development Status :: 3 - Alpha
Classifier: Intended Audience :: Developers
Classifier: Intended Audience :: Science/Research
Classifier: License :: OSI Approved :: MIT License
Classifier: Operating System :: OS Independent
Classifier: Programming Language :: Python :: 3
Classifier: Programming Language :: Python :: 3.12
Classifier: Programming Language :: Python :: 3.13
Classifier: Topic :: Internet :: WWW/HTTP :: Indexing/Search
Classifier: Topic :: Scientific/Engineering :: Information Analysis
Requires-Python: <3.14,>=3.12
Requires-Dist: pydantic-ai-slim[openrouter]>=1.0
Requires-Dist: pydantic-settings>=2.0
Requires-Dist: pydantic>=2.0
Provides-Extra: all
Requires-Dist: fastapi>=0.115; extra == 'all'
Requires-Dist: jinja2>=3.1; extra == 'all'
Requires-Dist: mcp>=1.0.0; extra == 'all'
Requires-Dist: python-dotenv>=1.0.0; extra == 'all'
Requires-Dist: typer>=0.12; extra == 'all'
Requires-Dist: uvicorn>=0.32; extra == 'all'
Provides-Extra: api
Requires-Dist: fastapi>=0.115; extra == 'api'
Requires-Dist: jinja2>=3.1; extra == 'api'
Requires-Dist: uvicorn>=0.32; extra == 'api'
Provides-Extra: cli
Requires-Dist: typer>=0.12; extra == 'cli'
Provides-Extra: mcp
Requires-Dist: mcp>=1.0.0; extra == 'mcp'
Requires-Dist: python-dotenv>=1.0.0; extra == 'mcp'
